exabgp/__init__.py
exabgp/__main__.py
exabgp/debug.py
exabgp/logger.py
exabgp/version.py
exabgp/application/__init__.py
exabgp/application/bgp.py
exabgp/application/cli.py
exabgp/application/control.py
exabgp/application/flow.py
exabgp/application/healthcheck.py
exabgp/application/netlink.py
exabgp/application/tojson.py
exabgp/bgp/__init__.py
exabgp/bgp/fsm.py
exabgp/bgp/neighbor.py
exabgp/bgp/timer.py
exabgp/bgp/message/__init__.py
exabgp/bgp/message/direction.py
exabgp/bgp/message/keepalive.py
exabgp/bgp/message/message.py
exabgp/bgp/message/nop.py
exabgp/bgp/message/notification.py
exabgp/bgp/message/operational.py
exabgp/bgp/message/refresh.py
exabgp/bgp/message/unknown.py
exabgp/bgp/message/open/__init__.py
exabgp/bgp/message/open/asn.py
exabgp/bgp/message/open/holdtime.py
exabgp/bgp/message/open/routerid.py
exabgp/bgp/message/open/version.py
exabgp/bgp/message/open/capability/__init__.py
exabgp/bgp/message/open/capability/addpath.py
exabgp/bgp/message/open/capability/asn4.py
exabgp/bgp/message/open/capability/capabilities.py
exabgp/bgp/message/open/capability/capability.py
exabgp/bgp/message/open/capability/extended.py
exabgp/bgp/message/open/capability/graceful.py
exabgp/bgp/message/open/capability/hostname.py
exabgp/bgp/message/open/capability/mp.py
exabgp/bgp/message/open/capability/ms.py
exabgp/bgp/message/open/capability/negotiated.py
exabgp/bgp/message/open/capability/nexthop.py
exabgp/bgp/message/open/capability/operational.py
exabgp/bgp/message/open/capability/refresh.py
exabgp/bgp/message/open/capability/unknown.py
exabgp/bgp/message/update/__init__.py
exabgp/bgp/message/update/eor.py
exabgp/bgp/message/update/attribute/__init__.py
exabgp/bgp/message/update/attribute/aggregator.py
exabgp/bgp/message/update/attribute/aigp.py
exabgp/bgp/message/update/attribute/aspath.py
exabgp/bgp/message/update/attribute/atomicaggregate.py
exabgp/bgp/message/update/attribute/attribute.py
exabgp/bgp/message/update/attribute/attributes.py
exabgp-4.1.2.dist-info/METADATA
exabgp-4.1.2.dist-info/WHEEL
exabgp-4.1.2.dist-info/entry_points.txt
exabgp-4.1.2.dist-info/top_level.txt
exabgp-4.1.2.dist-info/RECORD
