Metadata-Version: 2.1
Name: exabgp
Version: 4.1.2
Summary: BGP swiss army knife
Home-page: https://github.com/Exa-Networks/exabgp
Author: Thomas Mangin
Author-email: thomas.mangin@exa-networks.co.uk
License: BSD
Download-URL: https://github.com/Exa-Networks/exabgp/archive/4.1.2.tar.gz
Keywords: BGP routing SDN FlowSpec HA
Platform: macosx-10.14-x86_64
Classifier: Development Status :: 5 - Production/Stable
Classifier: Environment :: Console
Classifier: Intended Audience :: System Administrators
Classifier: Intended Audience :: Telecommunications Industry
Classifier: License :: OSI Approved :: BSD License
Classifier: Operating System :: POSIX
Classifier: Operating System :: MacOS :: MacOS X
Classifier: Programming Language :: Python
Classifier: Programming Language :: Python :: 3.7
Classifier: Topic :: Internet
